CHANGES.txt
buildout.cfg
setup.py
src/hurry/__init__.py
src/hurry.explorer.egg-info/PKG-INFO
src/hurry.explorer.egg-info/SOURCES.txt
src/hurry.explorer.egg-info/dependency_links.txt
src/hurry.explorer.egg-info/namespace_packages.txt
src/hurry.explorer.egg-info/not-zip-safe
src/hurry.explorer.egg-info/requires.txt
src/hurry.explorer.egg-info/top_level.txt
src/hurry/explorer/__init__.py
src/hurry/explorer/configure.zcml
src/hurry/explorer/explorer.py
src/hurry/explorer/resources/explorer.js