Metadata-Version: 1.0
Name: hurry.explorer
Version: 0.2
Summary: A (object) filesystem explorer UI built with YUI.
Home-page: UNKNOWN
Author: Martijn Faassen
Author-email: faassen@startifact.com
License: ZPL 2.1
Platform: UNKNOWN
